broker/__init__.py
broker/binds/__init__.py
broker/binds/beaker.py
broker/binds/containers.py
broker/binds/foreman.py
broker/binds/hussh.py
broker/binds/paramiko.py
broker/binds/pylibssh.py
broker/binds/ssh2.py
broker/binds/utils.py
broker/broker.py
broker/commands.py
broker/config_manager.py
broker/config_migrations/example_migration.py
broker/config_migrations/v0_6_0.py
broker/config_migrations/v0_6_12.py
broker/config_migrations/v0_6_3.py
broker/config_migrations/v0_6_9.py
broker/exceptions.py
broker/helpers/__init__.py
broker/helpers/dict_utils.py
broker/helpers/file_utils.py
broker/helpers/inventory.py
broker/helpers/misc.py
broker/helpers/results.py
broker/hosts.py
broker/logging.py
broker/providers/__init__.py
broker/providers/ansible_tower.py
broker/providers/beaker.py
broker/providers/container.py
broker/providers/foreman.py
broker/providers/openstack.py
broker/providers/test_provider.py
broker/scenario_schema.json
broker/scenarios.py
broker/session.py
broker/settings.py
broker-0.8.0.dist-info/WHEEL
broker-0.8.0.dist-info/entry_points.txt
broker-0.8.0.dist-info/METADATA
broker-0.8.0.dist-info/RECORD
