Metadata-Version: 2.3
Name: broker
Version: 0.8.0
Summary: The infrastructure middleman.
Keywords: broker,AnsibleTower,docker,podman,beaker,openstack
Author: Jacob J Callahan
Author-email: Jacob J Callahan <jacob.callahan05@gmail.com>
Classifier: Development Status :: 4 - Beta
Classifier: Intended Audience :: Developers
Classifier: Natural Language :: English
Classifier: Programming Language :: Python :: 3
Classifier: Programming Language :: Python :: 3.10
Classifier: Programming Language :: Python :: 3.11
Classifier: Programming Language :: Python :: 3.12
Classifier: Programming Language :: Python :: 3.13
Classifier: Programming Language :: Python :: 3.14
Requires-Dist: click
Requires-Dist: dynaconf>=3.1.6,<4.0.0
Requires-Dist: jinja2
Requires-Dist: jsonschema
Requires-Dist: packaging
Requires-Dist: python-json-logger
Requires-Dist: requests
Requires-Dist: rich
Requires-Dist: rich-click
Requires-Dist: ruamel-yaml
Requires-Dist: click-shell
Requires-Dist: typing-extensions
Requires-Dist: ansible-pylibssh ; extra == 'all'
Requires-Dist: awxkit ; extra == 'all'
Requires-Dist: beaker-client ; extra == 'all'
Requires-Dist: docker ; extra == 'all'
Requires-Dist: hussh>=0.1.7 ; extra == 'all'
Requires-Dist: openstacksdk ; extra == 'all'
Requires-Dist: paramiko ; extra == 'all'
Requires-Dist: pexpect ; extra == 'all'
Requires-Dist: pre-commit ; extra == 'all'
Requires-Dist: pytest ; extra == 'all'
Requires-Dist: pytest-randomly ; extra == 'all'
Requires-Dist: podman>=5.2 ; extra == 'all'
Requires-Dist: ruff ; extra == 'all'
Requires-Dist: ssh2-python ; extra == 'all'
Requires-Dist: ansible-pylibssh ; extra == 'ansible-pylibssh'
Requires-Dist: awxkit ; extra == 'ansibletower'
Requires-Dist: beaker-client ; extra == 'beaker'
Requires-Dist: docker ; extra == 'dev'
Requires-Dist: pexpect ; extra == 'dev'
Requires-Dist: pre-commit ; extra == 'dev'
Requires-Dist: pytest ; extra == 'dev'
Requires-Dist: pytest-randomly ; extra == 'dev'
Requires-Dist: ruff ; extra == 'dev'
Requires-Dist: tox ; extra == 'dev'
Requires-Dist: tox-uv ; extra == 'dev'
Requires-Dist: docker ; extra == 'docker'
Requires-Dist: paramiko ; extra == 'docker'
Requires-Dist: hussh>=0.1.7 ; extra == 'hussh'
Requires-Dist: openstacksdk ; extra == 'openstack'
Requires-Dist: paramiko ; extra == 'paramiko'
Requires-Dist: podman>=5.2 ; extra == 'podman'
Requires-Dist: awxkit ; extra == 'satlab'
Requires-Dist: podman>=5.2 ; extra == 'satlab'
Requires-Dist: hussh>=0.1.7 ; extra == 'satlab'
Requires-Dist: ssh2-python ; extra == 'ssh2-python'
Requires-Python: >=3.10
Project-URL: Repository, https://github.com/SatelliteQE/broker
Provides-Extra: all
Provides-Extra: ansible-pylibssh
Provides-Extra: ansibletower
Provides-Extra: beaker
Provides-Extra: dev
Provides-Extra: docker
Provides-Extra: hussh
Provides-Extra: openstack
Provides-Extra: paramiko
Provides-Extra: podman
Provides-Extra: satlab
Provides-Extra: ssh2-python
